httpx_limiter/__init__.py
httpx_limiter/_version.py
httpx_limiter/abstract_async_limiter.py
httpx_limiter/abstract_rate_limiter_repository.py
httpx_limiter/async_multi_rate_limited_transport.py
httpx_limiter/async_rate_limited_transport.py
httpx_limiter/py.typed
httpx_limiter/rate.py
httpx_limiter/types.py
httpx_limiter/aiolimiter/__init__.py
httpx_limiter/aiolimiter/aiolimiter_async_limiter.py
httpx_limiter/pyrate/__init__.py
httpx_limiter/pyrate/pyrate_async_limiter.py
httpx_limiter-0.5.0.dist-info/METADATA
httpx_limiter-0.5.0.dist-info/WHEEL
httpx_limiter-0.5.0.dist-info/licenses/LICENSE
httpx_limiter-0.5.0.dist-info/RECORD
