Metadata-Version: 2.4
Name: httpx-limiter
Version: 0.5.0
Summary: A lightweight package that provides rate-limited httpx transports.
Project-URL: Homepage, https://github.com/Midnighter/httpx-limiter
Project-URL: Documentation, https://httpx-limiter.readthedocs.io
Project-URL: Source Code, https://github.com/Midnighter/httpx-limiter
Project-URL: Bug Tracker, https://github.com/Midnighter/httpx-limiter/issues
Project-URL: Download, https://pypi.org/project/httpx-limiter/#files
Author-email: "Moritz E. Beber" <midnighter@posteo.net>
License-Expression: Apache-2.0
License-File: LICENSE
Keywords: httpx,leaky bucket,limiter,rate-limit
Classifier: Development Status :: 2 - Pre-Alpha
Classifier: Environment :: Web Environment
Classifier: Framework :: AsyncIO
Classifier: Intended Audience :: Developers
Classifier: License :: OSI Approved :: Apache Software License
Classifier: Natural Language :: English
Classifier: Operating System :: OS Independent
Classifier: Programming Language :: Python :: 3 :: Only
Classifier: Programming Language :: Python :: 3.10
Classifier: Programming Language :: Python :: 3.11
Classifier: Programming Language :: Python :: 3.12
Classifier: Programming Language :: Python :: 3.13
Classifier: Topic :: Internet :: WWW/HTTP
Classifier: Typing :: Typed
Requires-Python: >=3.10
Requires-Dist: httpx~=0.25
Requires-Dist: typing-extensions~=4.6; python_version < '3.11'
Provides-Extra: aiolimiter
Requires-Dist: aiolimiter~=1.2; extra == 'aiolimiter'
Provides-Extra: pyrate
Requires-Dist: pyrate-limiter~=3.9; extra == 'pyrate'
